README.rst
aiohttp_request.py
setup.cfg
setup.py
aiohttp_request.egg-info/PKG-INFO
aiohttp_request.egg-info/SOURCES.txt
aiohttp_request.egg-info/dependency_links.txt
aiohttp_request.egg-info/not-zip-safe
aiohttp_request.egg-info/requires.txt
aiohttp_request.egg-info/top_level.txt