Metadata-Version: 1.2
Name: aiohttp-request
Version: 0.0.2
Summary: Global request for aiohttp server
Home-page: https://github.com/hellysmile/aiohttp_request
Author: Victor Kovtun
Author-email: hellysmile@gmail.com
License: UNKNOWN
Keywords: aiohttp,request
Platform: UNKNOWN
Classifier: Development Status :: 4 - Beta
Classifier: Intended Audience :: Developers
Classifier: License :: OSI Approved :: MIT License
Classifier: Programming Language :: Python
Classifier: Programming Language :: Python :: 3
Classifier: Programming Language :: Python :: 3.7
Requires-Python: >=3.7.0
